LICENSE.txt
MANIFEST.in
README.md
README_pypi.md
pkgdata.txt
requirements.txt
setup.cfg
setup.py
ipytv/__init__.py
ipytv/channel.py
ipytv/doctor.py
ipytv/exceptions.py
ipytv/m3u.py
ipytv/playlist.py
ipytv/utils.py
ipytv/cli/__init__.py
ipytv/cli/iptv2json.py
ipytv/cli/json2iptv.py
ipytv/resources/schema.json
m3u_ipytv.egg-info/PKG-INFO
m3u_ipytv.egg-info/SOURCES.txt
m3u_ipytv.egg-info/dependency_links.txt
m3u_ipytv.egg-info/entry_points.txt
m3u_ipytv.egg-info/requires.txt
m3u_ipytv.egg-info/top_level.txt
tests/test_data.py