Metadata-Version: 2.4
Name: m3u_ipytv
Version: 1.0.0
Summary: A library for handling M3U playlists for IPTV (AKA m3u_plus)
Home-page: https://github.com/Beer4Ever83/ipytv
Author: Francesco Rainone
Author-email: beer4evah@gmail.com
License: MIT
Project-URL: Bug Reports, https://github.com/Beer4Ever83/ipytv/issues
Project-URL: Funding, https://www.buymeacoffee.com/beer4ever83
Project-URL: Source, https://github.com/Beer4Ever83/ipytv
Keywords: m3u,m3u_plus,iptv,playlist
Classifier: Development Status :: 5 - Production/Stable
Classifier: Intended Audience :: Developers
Classifier: Topic :: Software Development :: Libraries
Classifier: Topic :: Software Development :: Libraries :: Python Modules
Classifier: Topic :: Multimedia :: Video
Classifier: Programming Language :: Python :: 3
Requires-Python: >=3.6, <4
License-File: LICENSE.txt
Requires-Dist: requests>=2.31.0
Requires-Dist: click>=8.1.7
Requires-Dist: jsonschema>=4.23.0
Dynamic: author
Dynamic: author-email
Dynamic: classifier
Dynamic: description
Dynamic: description-content-type
Dynamic: home-page
Dynamic: keywords
Dynamic: license
Dynamic: license-file
Dynamic: project-url
Dynamic: requires-dist
Dynamic: requires-python
Dynamic: summary
